[
  {
    "command": "C:/mingw64/bin/g++.exe -c C:\\Uday\\codeliteWS\\project2\\main.cpp -o C:\\Uday\\codeliteWS\\project2\\main.cpp.o -target x86_64-w64-mingw32 -IC:\\mingw64\\include\\c++\\14.2.0 -IC:\\mingw64\\include\\c++\\14.2.0\\x86_64-w64-mingw32 -IC:\\mingw64\\include\\c++\\14.2.0\\backward -IC:\\mingw64\\lib\\gcc\\x86_64-w64-mingw32\\14.2.0\\include -IC:\\mingw64\\include -IC:\\mingw64\\lib\\gcc\\x86_64-w64-mingw32\\14.2.0\\include-fixed -IC:\\mingw64\\x86_64-w64-mingw32\\include -I. -I.  -gdwarf-2  -O0  -Wall",
    "directory": "C:\\Uday\\codeliteWS\\project2",
    "file": "C:\\Uday\\codeliteWS\\project2\\main.cpp"
  },
  {
    "command": "C:/mingw64/bin/g++.exe -c C:\\Uday\\codeliteWS\\project3\\main.cpp -o C:\\Uday\\codeliteWS\\project3\\main.cpp.o -target x86_64-w64-mingw32 -IC:\\mingw64\\include\\c++\\14.2.0 -IC:\\mingw64\\include\\c++\\14.2.0\\x86_64-w64-mingw32 -IC:\\mingw64\\include\\c++\\14.2.0\\backward -IC:\\mingw64\\lib\\gcc\\x86_64-w64-mingw32\\14.2.0\\include -IC:\\mingw64\\include -IC:\\mingw64\\lib\\gcc\\x86_64-w64-mingw32\\14.2.0\\include-fixed -IC:\\mingw64\\x86_64-w64-mingw32\\include -I. -I.  -gdwarf-2  -O0  -Wall",
    "directory": "C:\\Uday\\codeliteWS\\project3",
    "file": "C:\\Uday\\codeliteWS\\project3\\main.cpp"
  },
  {
    "command": "C:/mingw64/bin/g++.exe -c C:\\Uday\\codeliteWS\\project1\\main.cpp -o C:\\Uday\\codeliteWS\\project1\\main.cpp.o -target x86_64-w64-mingw32 -IC:\\mingw64\\include\\c++\\14.2.0 -IC:\\mingw64\\include\\c++\\14.2.0\\x86_64-w64-mingw32 -IC:\\mingw64\\include\\c++\\14.2.0\\backward -IC:\\mingw64\\lib\\gcc\\x86_64-w64-mingw32\\14.2.0\\include -IC:\\mingw64\\include -IC:\\mingw64\\lib\\gcc\\x86_64-w64-mingw32\\14.2.0\\include-fixed -IC:\\mingw64\\x86_64-w64-mingw32\\include -I. -I.  -O0  -gdwarf-2  -std=c++17  -Wall",
    "directory": "C:\\Uday\\codeliteWS\\project1",
    "file": "C:\\Uday\\codeliteWS\\project1\\main.cpp"
  }
]